btdcore/__init__.py
btdcore/cli.py
btdcore/logging.py
btdcore/py.typed
btdcore/request_persister_file.py
btdcore/rest_client_base.py
btdcore/utils.py
btdcore/aws/__init__.py
btdcore/aws/core.py
btdcore/aws/dynamo.py
btdcore/aws/request_persister_s3.py
btdcore/aws/s3_request_persister.py
btdcore/aws/s3bucket.py
btdcore-0.1.8.dist-info/METADATA
btdcore-0.1.8.dist-info/WHEEL
btdcore-0.1.8.dist-info/top_level.txt
btdcore-0.1.8.dist-info/RECORD
