Metadata-Version: 2.4
Name: btdcore
Version: 0.1.8
Summary: Core Python library for BlackTuskData
Author: Liam Tengelis
Author-email: liam.tengelis@blacktuskdata.com
Requires-Dist: pydantic
Requires-Dist: requests
Dynamic: author
Dynamic: author-email
Dynamic: requires-dist
Dynamic: summary
